loom/__init__.py
loom/app.py
loom/components.py
loom/magic.py
loom/state.py
loom_ui_pkg-0.1.1.dist-info/licenses/LICENCE
loom_ui_pkg-0.1.1.dist-info/METADATA
loom_ui_pkg-0.1.1.dist-info/WHEEL
loom_ui_pkg-0.1.1.dist-info/top_level.txt
loom_ui_pkg-0.1.1.dist-info/RECORD
