Metadata-Version: 2.4
Name: loom_ui_pkg
Version: 0.1.1
Summary: The Thread-Safe, State-Aware Interface that Weaves Itself.
Author-email: Scott Harvey-Whittle <scott@scott-hw.online>
Project-URL: Homepage, https://github.com/owner-scotthwcouk/LoomUI
Project-URL: Documentation, https://github.com/owner-scotthwcouk/loom-ui/blob/master/DOCS.md
Requires-Python: >=3.9
License-File: LICENCE
Requires-Dist: fastapi
Requires-Dist: uvicorn
Requires-Dist: websockets
Dynamic: license-file
